LICENSE
MANIFEST.in
README.rst
setup.py
upload.bat
radware_os_lb_v2_pike/__init__.py
radware_os_lb_v2_pike/another_lbaas_driver.py
radware_os_lb_v2_pike/base_driver.py
radware_os_lb_v2_pike/config.py
radware_os_lb_v2_pike/exceptions.py
radware_os_lb_v2_pike/radware_lbaas_driver.py
radware_os_lb_v2_pike/rest_client.py
radware_os_lb_v2_pike.egg-info/PKG-INFO
radware_os_lb_v2_pike.egg-info/SOURCES.txt
radware_os_lb_v2_pike.egg-info/dependency_links.txt
radware_os_lb_v2_pike.egg-info/not-zip-safe
radware_os_lb_v2_pike.egg-info/top_level.txt